<?xml version="1.0" encoding="UTF-8"?>
<resume>
  <ID>65</ID>
  <IsActive/>
  <PersonalInfo>
    <firstName>roula</firstName>
    <lastName>arab</lastName>
    <birthday/>
    <Nationality/>
    <MaritalStatus/>
    <gender/>
    <country-name/>
    <locality/>
    <street-address/>
    <Email/>
    <Telephone/>
  </PersonalInfo>
  <Education>
    <eduMajor>ITE</eduMajor>
    <eduMinor>Software Engineering</eduMinor>
    <eduStartDate>2013-09-01</eduStartDate>
    <eduGradDate>2018-08-01</eduGradDate>
    <studiedIn>Damascus University</studiedIn>
    <degreeType>EduBachelor</degreeType>
  </Education>
  <Education>
    <eduMajor>ITE</eduMajor>
    <eduMinor>AI</eduMinor>
    <eduStartDate>2018-08-02</eduStartDate>
    <eduGradDate>2020-09-01</eduGradDate>
    <studiedIn>Damascus University</studiedIn>
    <degreeType>EduMaster</degreeType>
  </Education>
  <WorkExperience>
    <employedIn/>
    <jobTitle/>
    <startDate/>
    <endDate/>
    <careerLevel/>
  </WorkExperience>
  <PersonalSkills>
    <skillName/>
    <skillYearsExperience/>
    <skillLevel/>
  </PersonalSkills>
  <Language>
    <Name/>
    <SpokenLevel/>
    <ReadingLevel/>
    <WritingLevel/>
  </Language>
  <References>
    <Name/>
    <Phone/>
    <Email/>
  </References>
</resume>
